README.txt
setup.py
dataStruct/__init__.py
dataStruct/positional_list.py
dataStructdut.egg-info/PKG-INFO
dataStructdut.egg-info/SOURCES.txt
dataStructdut.egg-info/dependency_links.txt
dataStructdut.egg-info/entry_points.txt
dataStructdut.egg-info/top_level.txt
dataStructdut.egg-info/zip-safe