Metadata-Version: 1.1
Name: dataStructdut
Version: 1.0.2
Summary: This package provides all kinds of dataStructs.
Home-page: https://github.com/ChinaVeryNb/dataStruct.git
Author: tjg
Author-email: 1205322591@qq.com
License: MIT
Keywords: dataStruct,dut
Platform: UNKNOWN
Classifier: License :: OSI Approved :: MIT License
Classifier: Programming Language :: Python
Classifier: Intended Audience :: Developers
Classifier: Operating System :: OS Independent
